repono/__init__.py
repono/exceptions.py
repono/file_item.py
repono/filter_base.py
repono/filters/__init__.py
repono/filters/py.typed
repono/filters/randomize_filename.py
repono/filters/valid_extensions.py
repono/handler_base.py
repono/handlers/__init__.py
repono/handlers/dummy.py
repono/handlers/file.py
repono/handlers/py.typed
repono/handlers/s3.py
repono/py.typed
repono/storage_container.py
repono/utils.py
repono-0.0.6.dist-info/LICENSE
repono-0.0.6.dist-info/WHEEL
repono-0.0.6.dist-info/METADATA
repono-0.0.6.dist-info/RECORD
