Metadata-Version: 2.1
Name: repono
Version: 0.0.6
Summary: Save uploaded files in configurable stores
Home-page: https://github.com/avoco/repono
License: MIT
Keywords: file-system,async,starlette,fastapi
Author: Ian Epperson
Author-email: ian@epperson.com
Requires-Python: >=3.8,<4.0
Classifier: License :: OSI Approved :: MIT License
Classifier: Operating System :: OS Independent
Classifier: Programming Language :: Python :: 3
Classifier: Programming Language :: Python :: 3.10
Classifier: Programming Language :: Python :: 3.8
Classifier: Programming Language :: Python :: 3.9
Provides-Extra: aiofile
Provides-Extra: s3
Requires-Dist: aioboto3 (>=8.3.0,<9.0.0); extra == "s3"
Requires-Dist: aiofiles (>=0.6.0,<0.7.0); extra == "aiofile"
Requires-Dist: asgiref (>=3.3.1,<4.0.0)
Requires-Dist: click (>=7.1.2,<8.0.0)
Project-URL: Repository, https://github.com/avoco/repono
